{"O/FyccKnPDEvC3zmN9dygA==":"mbr.jpg","SpXFDT0eHkZzlReedWpseA==":"whatsapp%20image%202021-06-15%20at%207.44.24%20am-1042x1028.jpeg","HwZfjrgnZ8Eai2vzXNtz0Q==":"whatsapp%20image%202021-06-15%20at%207.44.25%20am-1076x716.jpg","1G9hM7knZgHicTS+hzOaEQ==":"whatsapp%20image%202021-06-15%20at%207.44.24%20am-1042x1028.jpg","Pyb8QjmtjXjZiBh9oVHGEg==":"whatsapp%20image%202021-06-15%20at%207.44.28%20am-1080x719.jpg","f3lsQbkSuafMN58RdjlMfg==":"whatsapp%20image%202021-06-15%20at%207.44.24%20am-1042x1028.jpg","ekwmr/Zysd5l+VD6uSHe/g==":"mbr-1920x1280.jpg","DVhO+/s+woQAS6NuYnyxHw==":"whatsapp%20image%202021-06-15%20at%207.46.19%20am-696x464.jpg","r1OHvtgz9HAB2yrBr+YzQg==":"whatsapp%20image%202021-06-15%20at%207.44.23%20am-696x463.jpg","DtBWue6esMkF4kgyBNJpjw==":"whatsapp%20image%202021-06-15%20at%207.44.30%20am%20(1)-696x463.jpg","nzIa5SVXDAAiwBEn7y8dfA==":"whatsapp%20image%202021-06-15%20at%207.44.34%20am-696x382.jpg","c7kE7g4+Qxs66TGa48omHQ==":"whatsapp%20image%202021-06-15%20at%207.44.28%20am-696x463.jpg","uv7tpFDQrPgt7HuhgxrvBA==":"whatsapp%20image%202021-06-15%20at%207.44.26%20am-696x500.jpg","xWGXSsqQCow51mubwe9QdQ==":"shutterstock_566238307-compressor-696x364.jpg","WaInc4oXdVu+WnO134qPUQ==":"11052-yet-rejoice-696x364.png","FUvD0ldOd9Zu/CEeL5AExw==":"50540_1_tool.webp","YuLTrFP1ItY+VMvF7Hrfkw==":"failure-learning-mistakes-696x464.jpg","znf0lC8ol3FKIvYBjjZjjw==":"failure-learning-mistakes-696x464.jpeg","Vb7GgbMoe0curpGYBParsg==":"background3.jpg","Xem/QKmQI791J+yLhQhY4A==":"maxresdefault-696x391.jpg","QPfuDtYxa+m6w83dIEY6hw==":"evangelism-tell-your-story-hero-1280x720.png","6oqP+o2lNtMDR7so5IlaFA==":"testimony-1920x1080.jpeg","y7+wPZRyW38ywOFUWKK77Q==":"supernatural-web-400x225.jpg","4YBiyyVbvCkMUgMTTGrGEQ==":"supernatural-web-400x225.jpeg","kzj7mi2H1FSO+FmaHRNA+Q==":"get%20healed%20now!%20it's%20possible%20now!!%20ark%20of%20greatness,%20father%20okwuosa-400x261.jpg","zrKvBuQEgruBREUCAXmAnQ==":"whatsapp%20image%202021-06-16%20at%2011.53.56%20am-886x709.jpg","nV+F28ncQ4N5bb9k5AujOg==":"delay-4_0-3-450x300.jpg","iIKabHqvR3AGw5C6pGOg7g==":"https%20_specials-images.forbesimg.com_dam_imageserve_1142988437_0x0.jpg%20fit=scale-696x522.jpg","ZRPZwAgPlI6KI1TGAQ3Z5A==":"blessedmeasure1-696x407.jpg","0yAhHjMP5vn8fF/JKhvDkw==":"blessedmeasure1-696x696.jpg","EH6CxVCeM8MiOJqKnKxsfg==":"32%20prayers%20points%20to%20remember%20your%20dream%20by%20father%20henry%20okwuosa,%20ark%20of%20greatness-650x366.jpg","M14antrquUejJ8sIm+PAgA==":"green-pastures-2-696x434.jpg","fdPacMxARkBnGrFWRaPmEA==":"artboard%201-96x96.png","bqdHAUyb7WPz9ttkgEKCeQ==":"artboard%201@2x-96x96.png","bKqoA7cQu1hHQt6pvKfLMg==":"whatsapp%20image%202021-06-17%20at%207.55.35%20am-96x96.jpg","QNiBDfodlecIuKnoZUO7oQ==":"mbr-1-1920x1280.jpg","lDk4pUbZXltNHeZUv9k+aA==":"artboard%201@2x-96x96.png","45Ofbs8u3KFGNiAM6CDl0g==":"artboard%201-844x844.png","0g5iUCpQb66qfInBpkWC7g==":"relationship-696x464.jpg","aN7YDHHYlUC1NfZvvIphVQ==":"1592526476911-3072x1536.jpg","9Qg1iqDDsmweefw6cKDF1Q==":"1592526476911-3072x1536.jpeg","S9G/cKS+F36coADjBajK9Q==":"1140-ways-to-give-donate-falling-coins-hands.web-1140x655.jpg","wKqW8bMo00p2s52j5vYQPA==":"2014-2-696x696.jpg","9kZrFL2aAvOWVCNNn1PAoA==":"favour-of-god-696x474.jpg","8wuYam04Z+QD7tnQHNO38A==":"whatsapp%20image%202021-06-15%20at%207.46.19%20am-1080x720.jpg","eg+oZq0VhJssrpbP/9yHww==":"whatsapp%20image%202021-06-15%20at%207.37.11%20am-1080x719.jpg","EhzLy+WZZRbggoNcu7pLYQ==":"whatsapp%20image%202021-06-15%20at%207.44.29%20am-1076x716.jpg","t/gBxgqMCP2zLlsRhenBUA==":"whatsapp%20image%202021-06-15%20at%207.37.13%20am-1076x716.jpg","mPxdnujHcSXKmAYDxxNTyQ==":"whatsapp%20image%202021-06-15%20at%207.37.11%20am-1076x716.jpg","P5OYq8X74iGiWa4rqd2Lpg==":"whatsapp%20image%202021-06-15%20at%207.44.22%20am-1076x716.jpg","OUbIcgrtt9YkA0C7WrF5AQ==":"whatsapp%20image%202021-06-15%20at%207.44.25%20am%20(1)-1080x719.jpg","v+N6S8+AoQmoXNrdcq7Xmw==":"whatsapp%20image%202021-06-15%20at%207.44.26%20am-1080x776.jpg"}